s100py/__init__.py
s100py/s1xx.py
s100py/s100/__init__.py
s100py/s100/s100.py
s100py/s100/v4_0/__init__.py
s100py/s100/v4_0/api.py
s100py/s100/v5_0/__init__.py
s100py/s100/v5_0/api.py
s100py/s100/v5_1/__init__.py
s100py/s100/v5_1/api.py
s100py/s100/v5_2/__init__.py
s100py/s100/v5_2/api.py
s100py/s102/README.md
s100py/s102/__init__.py
s100py/s102/api.py
s100py/s102/make_s102.spec
s100py/s102/readme_build_an_exe.txt
s100py/s102/utils.py
s100py/s102/v2_0/__init__.py
s100py/s102/v2_0/api.py
s100py/s102/v2_0/utils.py
s100py/s102/v2_1/__init__.py
s100py/s102/v2_1/api.py
s100py/s102/v2_1/utils.py
s100py/s102/v2_2/__init__.py
s100py/s102/v2_2/api.py
s100py/s102/v2_2/utils.py
s100py/s102/v3_0/__init__.py
s100py/s102/v3_0/api.py
s100py/s102/v3_0/utils.py
s100py/s104/README.md
s100py/s104/__init__.py
s100py/s104/api.py
s100py/s104/utils.py
s100py/s104/v1_0/__init__.py
s100py/s104/v1_0/api.py
s100py/s104/v1_0/utils.py
s100py/s104/v1_1/__init__.py
s100py/s104/v1_1/api.py
s100py/s104/v1_1/utils.py
s100py/s104/v2_0/__init__.py
s100py/s104/v2_0/api.py
s100py/s104/v2_0/utils.py
s100py/s111/README.md
s100py/s111/__init__.py
s100py/s111/api.py
s100py/s111/utils.py
s100py/s111/v1_0/__init__.py
s100py/s111/v1_0/api.py
s100py/s111/v1_0/utils.py
s100py/s111/v1_2/__init__.py
s100py/s111/v1_2/api.py
s100py/s111/v1_2/utils.py
s100py/s111/v2_0/__init__.py
s100py/s111/v2_0/api.py
s100py/s111/v2_0/utils.py
s100py-2.0.1.dist-info/LICENSE
s100py-2.0.1.dist-info/METADATA
s100py-2.0.1.dist-info/WHEEL
s100py-2.0.1.dist-info/top_level.txt
s100py-2.0.1.dist-info/RECORD
