Metadata-Version: 2.1
Name: s100py
Version: 2.0.1
Summary: This python package provides api and utilities for encoding hydrographic datasets in the International Hydrographic Organization (IHO) S-100 format
Author-email: Barry Gallagher <barry.gallagher@noaa.gov>, Erin Nagel <erin.nagel@noaa.gov>
Project-URL: Homepage, https://github.com/noaa-ocs-s100/s100py
Project-URL: Bug Tracker, https://github.com/noaa-ocs-s100/s100py/issues/
Project-URL: Documentation, https://s100py.readthedocs.io/en/latest/
Project-URL: Source, https://github.com/noaa-ocs-s100/s100py
Keywords: S-100,S-102,S-111,S-104,hydrographic
Classifier: Programming Language :: Python :: 3
Classifier: Intended Audience :: Science/Research
Classifier: License :: CC0 1.0 Universal (CC0 1.0) Public Domain Dedication
Classifier: Operating System :: OS Independent
Requires-Python: >=3.8
License-File: LICENSE
Requires-Dist: h5py
Requires-Dist: numpy
